dsd_heroku/__init__.py
dsd_heroku/deploy.py
dsd_heroku/deploy_messages.py
dsd_heroku/platform_deployer.py
dsd_heroku/plugin_config.py
dsd_heroku/templates/settings.py
dsd_heroku/templates/settings_wagtail.py
dsd_heroku-1.1.0.dist-info/licenses/LICENSE
dsd_heroku-1.1.0.dist-info/METADATA
dsd_heroku-1.1.0.dist-info/WHEEL
dsd_heroku-1.1.0.dist-info/top_level.txt
dsd_heroku-1.1.0.dist-info/RECORD
