Metadata-Version: 2.4
Name: dsd-heroku
Version: 1.1.0
Summary: A plugin for django-simple-deploy, supporting deployments to Heroku.
Author-email: Eric Matthes <ehmatthes@gmail.com>
Project-URL: Documentation, https://github.com/django-simple-deploy/dsd-heroku
Project-URL: GitHub, https://github.com/django-simple-deploy/dsd-heroku
Project-URL: Changelog, https://github.com/django-simple-deploy/dsd-heroku/blob/main/CHANGELOG.md
Keywords: django,deployment
Classifier: Development Status :: 4 - Beta
Classifier: Framework :: Django :: 4.2
Classifier: Framework :: Django :: 5.0
Classifier: Framework :: Django :: 5.1
Classifier: Intended Audience :: Developers
Classifier: License :: OSI Approved :: BSD License
Classifier: Operating System :: OS Independent
Classifier: Programming Language :: Python :: 3 :: Only
Classifier: Programming Language :: Python :: 3.9
Classifier: Programming Language :: Python :: 3.10
Classifier: Programming Language :: Python :: 3.11
Classifier: Programming Language :: Python :: 3.12
Classifier: Programming Language :: Python :: 3.13
Requires-Python: >=3.9
License-File: LICENSE
Requires-Dist: django>=4.2
Requires-Dist: pluggy>=1.5.0
Requires-Dist: toml>=0.10.2
Requires-Dist: requests>=2.32.2
Requires-Dist: django-simple-deploy>=0.9.4
Provides-Extra: dev
Requires-Dist: black>=24.1.0; extra == "dev"
Requires-Dist: build>=1.2.1; extra == "dev"
Requires-Dist: pytest>=8.3.0; extra == "dev"
Requires-Dist: twine>=5.1.1; extra == "dev"
Dynamic: license-file
